[
    {"english": "zero", "chinese": "0", "phonetics": "[ˈzɪro]", "example": "Five minus five equals zero."},
    {"english": "one", "chinese": "1", "phonetics": "[wʌn]", "example": "Ten divided by ten is one."},
    {"english": "two", "chinese": "2", "phonetics": "[tu]", "example": "What is two plus zero?"},
    {"english": "three", "chinese": "3", "phonetics": "[θri]", "example": "One plus two makes three."},
    {"english": "four", "chinese": "4", "phonetics": "[for]", "example": "Eight divided by two is four."},
    {"english": "five", "chinese": "5", "phonetics": "[faɪv]", "example": "Two plus three equals five."},
    {"english": "six", "chinese": "6", "phonetics": "[sɪks]", "example": "What is three times two? It's six."},
    {"english": "seven", "chinese": "7", "phonetics": "[ˈsɛvən]", "example": "Ten minus three is seven."},
    {"english": "eight", "chinese": "8", "phonetics": "[et]", "example": "Four times two equals eight."},
    {"english": "nine", "chinese": "9", "phonetics": "[naɪn]", "example": "What is three times three? It's nine."},
    {"english": "ten", "chinese": "10", "phonetics": "[tɛn]", "example": "Five times two is ten."},
    {"english": "eleven", "chinese": "11", "phonetics": "[ɪˈlɛvən]", "example": "Twenty minus nine equals eleven."},
    {"english": "twelve", "chinese": "12", "phonetics": "[twɛlv]", "example": "What is six times two? It's twelve."},
    {"english": "thirteen", "chinese": "13", "phonetics": "[ˌθɝˈtin]", "example": "Seven plus six is thirteen."},
    {"english": "fourteen", "chinese": "14", "phonetics": "[ˌforˈtin]", "example": "What is twenty minus six? It's fourteen."},
    {"english": "fifteen", "chinese": "15", "phonetics": "[ˌfɪfˈtin]", "example": "Three times five equals fifteen."},
    {"english": "sixteen", "chinese": "16", "phonetics": "[ˌsɪksˈtin]", "example": "What is thirty-two divided by two? It's sixteen."},
    {"english": "seventeen", "chinese": "17", "phonetics": "[ˌsɛvənˈtin]", "example": "Ten plus seven makes seventeen."},
    {"english": "eighteen", "chinese": "18", "phonetics": "[ˌeˈtin]", "example": "Nine times two is eighteen."},
    {"english": "nineteen", "chinese": "19", "phonetics": "[ˌnaɪnˈtin]", "example": "What is twenty-five minus six? It's nineteen."},
    {"english": "twenty", "chinese": "20", "phonetics": "[ˈtwɛnti]", "example": "Ten plus ten equals twenty."},
    {"english": "thirty", "chinese": "30", "phonetics": "[ˈθɝti]", "example": "What is fifty minus twenty? It's thirty."},
    {"english": "forty", "chinese": "40", "phonetics": "[ˈforti]", "example": "Eighty divided by two is forty."},
    {"english": "fifty", "chinese": "50", "phonetics": "[ˈfɪfti]", "example": "What is one hundred divided by two? It's fifty."},
    {"english": "sixty", "chinese": "60", "phonetics": "[ˈsɪksti]", "example": "Thirty times two equals sixty."},
    {"english": "seventy", "chinese": "70", "phonetics": "[ˈsɛvənti]", "example": "What is ninety minus twenty? It's seventy."},
    {"english": "eighty", "chinese": "80", "phonetics": "[ˈeti]", "example": "Forty plus forty is eighty."},
    {"english": "ninety", "chinese": "90", "phonetics": "[ˈnaɪnti]", "example": "What is thirty times three? It's ninety."},
    {"english": "twenty-seven", "chinese": "27", "phonetics": "[ˈtwɛnti ˈsɛvən]", "example": "Thirty minus three equals twenty-seven."},
    {"english": "forty-four", "chinese": "44", "phonetics": "[ˈforti for]", "example": "Eleven times four is forty-four."}
]