[
  {
    "english": "like",
    "chinese": "喜歡；像...",
    "phonetics": "[laɪk]",
    "example": "I like this park. It is big and beautiful."
  },
  {
    "english": "sport",
    "chinese": "運動",
    "phonetics": "[spɔrt]",
    "example": "Terry plays sports in his free time."
  },
  {
    "english": "much",
    "chinese": "多（的）",
    "phonetics": "[mʌtʃ]",
    "example": "Hurry up! We don't have much time."
  },
  {
    "english": "team",
    "chinese": "隊；組",
    "phonetics": "[tim]",
    "example": "Frank is on the school baseball team."
  },
  {
    "english": "practice",
    "chinese": "練習",
    "phonetics": "[`præktɪs]",
    "example": "Jack practices basketball after school every day."
  },
  {
    "english": "every",
    "chinese": "每一",
    "phonetics": "[`ɛvrɪ]",
    "example": "I wash my book bag every six months."
  },
  {
    "english": "then",
    "chinese": "那麼",
    "phonetics": "[ðɛn]",
    "example": "A: I don't watch TV. B: Really? Then what do you do in your free time?"
  },
  {
    "english": "swim",
    "chinese": "游泳",
    "phonetics": "[swɪm]",
    "example": "A: What is that bear doing? B: It is swimming."
  },
  {
    "english": "join",
    "chinese": "參加",
    "phonetics": "[dʒɔɪn]",
    "example": "A: Can I join your team? B: Sure. Welcome!"
  },
  {
    "english": "eye",
    "chinese": "眼睛",
    "phonetics": "[aɪ]",
    "example": "Camila has beautiful brown eyes."
  },
  {
    "english": "hair",
    "chinese": "頭髮",
    "phonetics": "[hɛr]",
    "example": "A: I like your hair color. B: Thank you."
  },
  {
    "english": "know",
    "chinese": "知道；認識",
    "phonetics": "[no]",
    "example": "A: Do you know Viola? B: Viola Huang? Yeah. She is my cousin."
  },
  {
    "english": "hundred",
    "chinese": "百",
    "phonetics": "[`hʌndrəd]",
    "example": "There are nine hundred students in my school."
  },
  {
    "english": "centimeter",
    "chinese": "公分 (= cm)",
    "phonetics": "[`sɛntəˌmitɚ]",
    "example": "The ruler is fifteen centimeters long."
  },
  {
    "english": "You can say that again!",
    "chinese": "一點也沒錯！",
    "phonetics": "[ju kən ˌse `ðæt ə`gɛn]",
    "example": "A: That band is really popular in the USA. B: You can say that again!"
  },
  {
    "english": "guitar",
    "chinese": "吉他",
    "phonetics": "[gɪ`tɑr]",
    "example": "My sister practices the guitar in her room."
  },
  {
    "english": "piano",
    "chinese": "鋼琴",
    "phonetics": "[pɪ`æno]",
    "example": "Many students in the class can play the piano."
  },
  {
    "english": "fly a kite",
    "chinese": "放風箏",
    "phonetics": "[ˌflaɪ ə `kaɪt]",
    "example": "The boy is flying a kite."
  },
  {
    "english": "paint",
    "chinese": "畫圖；顏料；油漆",
    "phonetics": "[pent]",
    "example": "A: What can you do? B: I can paint the walls."
  },
  {
    "english": "make a cake",
    "chinese": "做蛋糕",
    "phonetics": "[ˌmek ə `kek]",
    "example": "A: We can make a cake for Sue's birthday. B: Yeah, let's do it."
  },
  {
    "english": "nose",
    "chinese": "鼻子",
    "phonetics": "[noz]",
    "example": "Pinocchio's nose is long and thin."
  },
  {
    "english": "leg",
    "chinese": "腿",
    "phonetics": "[lɛg]",
    "example": "My legs are 90 centimeters long."
  },
  {
    "english": "large",
    "chinese": "大的",
    "phonetics": "[lɑrdʒ]",
    "example": "This house is large for my family."
  },
  {
    "english": "ear",
    "chinese": "耳朵",
    "phonetics": "[ɪr]",
    "example": "The dog's ears are very big."
  },
  {
    "english": "mouth",
    "chinese": "嘴巴",
    "phonetics": "[maʊθ]",
    "example": "Don't talk with your mouth full."
  },
  {
    "english": "thick",
    "chinese": "厚的",
    "phonetics": "[θɪk]",
    "example": "Harry has many thick books."
  },
  {
    "english": "lip",
    "chinese": "嘴唇",
    "phonetics": "[lɪp]",
    "example": "Dogs' lips are black."
  },
  {
    "english": "strong",
    "chinese": "強壯的",
    "phonetics": "[strɔŋ]",
    "example": "These bugs are small but strong."
  },
  {
    "english": "arm",
    "chinese": "手臂",
    "phonetics": "[ɑrm]",
    "example": "Those monkeys have really long arms."
  },
  {
    "english": "height",
    "chinese": "身高；高度",
    "phonetics": "[haɪt]",
    "example": "The doghouse is 50 centimeters in height."
  },
  {
    "english": "player",
    "chinese": "選手；球員",
    "phonetics": "[`pleɚ]",
    "example": "That handsome man over there is Zoe's favorite baseball player."
  },
  {
    "english": "the USA",
    "chinese": "美國",
    "phonetics": "[ðə `ju `ɛs `e] (= the United States of America)",
    "example": "The girl band comes from the USA."
  },
  {
    "english": "body",
    "chinese": "身體",
    "phonetics": "[`bɑdɪ]",
    "example": "He has a strong body."
  },
  {
    "english": "put one's all",
    "chinese": "盡全力",
    "phonetics": "[pʊt wʌnz `ɔl]",
    "example": "Jeremy puts his all into every game."
  },
  {
    "english": "into",
    "chinese": "到...裡面",
    "phonetics": "[`ɪntə]",
    "example": "Please put your pencils into the pencil case."
  },
  {
    "english": "a lot of",
    "chinese": "很多的 (= lots of)",
    "phonetics": "[ə `lɑt əv]",
    "example": "Grandma cooks a lot of food for us on Thanksgiving every year."
  },
  {
    "english": "stand out",
    "chinese": "突出",
    "phonetics": "[ˌstænd `aʊt]",
    "example": "The black picture on the orange wall really stands out."
  },
  {
    "english": "different",
    "chinese": "不同的",
    "phonetics": "[`dɪf(ə)rənt]",
    "example": "Vincent is very different from his brother."
  },
  {
    "english": "top",
    "chinese": "頂尖的",
    "phonetics": "[tɑp]",
    "example": "My brothers both go to top schools."
  },
  {
    "english": "on the other hand",
    "chinese": "另一方面",
    "phonetics": "[ˌɑn ðɪ `ʌðɚ hænd]",
    "example": "Adam is very good at basketball. On the other hand, he's new to baseball."
  },
  {
    "english": "make up for...",
    "chinese": "彌補...",
    "phonetics": "[mek `ʌp ˌfɔr]",
    "example": "For a baseball player, he's not very strong, but he makes up for it with a lot of practice."
  }
]